LICENCE
README.md
setup.py
amis_admin_theme_editor/__init__.py
amis_admin_theme_editor/admin.py
amis_admin_theme_editor/editor.py
amis_admin_theme_editor/helper.py
amis_admin_theme_editor/model.py
amis_admin_theme_editor.egg-info/PKG-INFO
amis_admin_theme_editor.egg-info/SOURCES.txt
amis_admin_theme_editor.egg-info/dependency_links.txt
amis_admin_theme_editor.egg-info/top_level.txt
amis_admin_theme_editor.egg-info/zip-safe